jewels/__init__.py
jewels/jewels.py
jewels-1.1.4.data/scripts/jewels-cli
jewels-1.1.4.dist-info/LICENSE
jewels-1.1.4.dist-info/METADATA
jewels-1.1.4.dist-info/WHEEL
jewels-1.1.4.dist-info/top_level.txt
jewels-1.1.4.dist-info/RECORD
