Metadata-Version: 2.1
Name: jewels
Version: 1.1.4
Summary: Secure file encryption and data access
Home-page: https://github.com/acapitanelli/jewels
Author: andrea capitanelli
Author-email: andrea.capitanelli@gmail.com
Maintainer: andrea capitanelli
Maintainer-email: andrea.capitanelli@gmail.com
License: MIT
Keywords: data file encryption aes256 eax cli
Platform: UNKNOWN
Classifier: Development Status :: 5 - Production/Stable
Classifier: License :: OSI Approved :: MIT License
Classifier: Programming Language :: Python :: 3
Classifier: Topic :: Security :: Cryptography
Requires-Dist: pycryptodome
